LICENSE
MANIFEST.in
README.md
pylintrc
setup.cfg
setup.py
gymnast/VERSION
gymnast/__init__.py
gymnast/exc.py
gymnast/misc.py
gymnast/pdf_codec.py
gymnast/pdf_constants.py
gymnast/pdf_doc.py
gymnast/pdf_matrix.py
gymnast/pdf_parser.py
gymnast.egg-info/PKG-INFO
gymnast.egg-info/SOURCES.txt
gymnast.egg-info/dependency_links.txt
gymnast.egg-info/requires.txt
gymnast.egg-info/top_level.txt
gymnast/data/glyphlist.txt
gymnast/data/pdf_encodings.txt
gymnast/data/afm/Courier-Bold.afm
gymnast/data/afm/Courier-BoldOblique.afm
gymnast/data/afm/Courier-Oblique.afm
gymnast/data/afm/Courier.afm
gymnast/data/afm/Helvetica-Bold.afm
gymnast/data/afm/Helvetica-BoldOblique.afm
gymnast/data/afm/Helvetica-Oblique.afm
gymnast/data/afm/Helvetica.afm
gymnast/data/afm/MustRead.html
gymnast/data/afm/README
gymnast/data/afm/Symbol.afm
gymnast/data/afm/Times-Bold.afm
gymnast/data/afm/Times-BoldItalic.afm
gymnast/data/afm/Times-Italic.afm
gymnast/data/afm/Times-Roman.afm
gymnast/data/afm/ZapfDingbats.afm
gymnast/filters/__init__.py
gymnast/filters/filters.py
gymnast/filters/stream_filter.py
gymnast/pdf_elements/__init__.py
gymnast/pdf_elements/other_elements.py
gymnast/pdf_elements/pdf_element.py
gymnast/pdf_elements/pdf_page.py
gymnast/pdf_elements/fonts/__init__.py
gymnast/pdf_elements/fonts/base_font.py
gymnast/pdf_elements/fonts/pdf_font.py
gymnast/pdf_elements/fonts/true_type.py
gymnast/pdf_elements/fonts/type1.py
gymnast/pdf_elements/fonts/type3.py
gymnast/pdf_operation/__init__.py
gymnast/pdf_operation/pdf_operation.py
gymnast/pdf_operation/operations/__init__.py
gymnast/pdf_operation/operations/special_graphics.py
gymnast/pdf_operation/operations/text_objects.py
gymnast/pdf_operation/operations/text_positioning.py
gymnast/pdf_operation/operations/text_showing.py
gymnast/pdf_operation/operations/text_state.py
gymnast/pdf_types/__init__.py
gymnast/pdf_types/common.py
gymnast/pdf_types/compound_types.py
gymnast/pdf_types/object_types.py
gymnast/pdf_types/simple_types.py
gymnast/pdf_types/streams.py
gymnast/pdf_types/string_types.py
gymnast/pdf_types/structural_types.py
gymnast/renderer/__init__.py
gymnast/renderer/base_renderer.py
