Metadata-Version: 1.1
Name: gymnast
Version: 0.1a5
Summary: Gymnast: PDF document parser in Python 3
Home-page: https://github.com/ajmarks/gymnast/
Author: Andrew Marks
Author-email: ajmarks@gmail.com
License: MIT License
Download-URL: https://github.com/ajmarks/gymnast/tarball/0.1a5
Keywords: pdf,acrobat
Platform: UNKNOWN
Classifier: Development Status :: 3 - Alpha
Classifier: Intended Audience :: Developers
Classifier: License :: OSI Approved :: MIT License
Classifier: Natural Language :: English
Classifier: Operating System :: OS Independent
Classifier: Programming Language :: Python :: 3 :: Only
Classifier: Programming Language :: Python :: 3.3
Classifier: Programming Language :: Python :: 3.4
Classifier: Programming Language :: Python :: 3.5
Classifier: Topic :: Text Processing
Classifier: Topic :: Utilities
